[{"name":"﻿ঢাকা মহানগর","count":"৭৬৮৪"},{"name":"নারায়ণগঞ্জ","count":"১২৮৬"},{"name":"গাজীপুর","count":"৩৪৭"},{"name":"চট্টগ্রাম","count":"৩১৪"},{"name":"ময়মনসিংহ","count":"২৪৬"},{"name":"ঢাকা","count":"২৩৮"},{"name":"মুন্সিগঞ্জ","count":"২১৭"},{"name":"কিশোরগঞ্জ","count":"২০৫"},{"name":"কুমিল্লা","count":"১৮৬"},{"name":"নরসিংদী","count":"১৭২"},{"name":"রংপুর","count":"১৪৩"},{"name":"জামালপুর","count":"১১০"},{"name":"কক্সবাজার","count":"১০৭"},{"name":"যশোর","count":"৮৪"},{"name":"হবিগঞ্জ","count":"৮১"},{"name":"নেত্রকোণা","count":"৮১"},{"name":"লক্ষ্মীপুর","count":"৭৪"},{"name":"গোপালগঞ্জ","count":"৬২"},{"name":"শরিয়তপুর","count":"৬০"},{"name":"নোয়াখালী","count":"৫৯"},{"name":"ব্রাহ্মণবাড়িয়া","count":"৫৮"},{"name":"মাদারিপুর","count":"৫৭"},{"name":"বরিশাল","count":"৫৬"},{"name":"চাঁদপুর","count":"৫৬"},{"name":"জয়পুরহাট","count":"৫৫"},{"name":"দিনাজপুর","count":"৪৩"},{"name":"নীলফামারী","count":"৪৩"},{"name":"সুনামগঞ্জ","count":"৪৩"},{"name":"ঝিনাইদহ","count":"৪১"},{"name":"শেরপুর","count":"৩৯"},{"name":"সিলেট","count":"৩৯"},{"name":"বরগুনা","count":"৩৭"},{"name":"কুড়িগ্রাম","count":"৩৬"},{"name":"মৌলভীবাজার","count":"৩৬"},{"name":"নওগাঁ","count":"৩৩"},{"name":"ফরিদপুর","count":"৩২"},{"name":"টাঙ্গাইল","count":"৩২"},{"name":"চুয়াডাঙ্গা","count":"৩০"},{"name":"মানিকগঞ্জ","count":"২৯"},{"name":"পটুয়াখালী","count":"২৯"},{"name":"রাজশাহী","count":"২৭"},{"name":"গাইবান্ধা","count":"২৫"},{"name":"ঠাকুরগাঁও","count":"২৪"},{"name":"রাজবাড়ী","count":"২৩"},{"name":"কুষ্টিয়া","count":"২৩"},{"name":"খুলনা","count":"২২"},{"name":"বগুড়া","count":"১৮"},{"name":"পাবনা","count":"১৮"},{"name":"মাগুরা","count":"১৮"},{"name":"চাঁপাইনবাবগঞ্জ","count":"১৫"},{"name":"লালমনিরহাট","count":"১৫"},{"name":"নড়াইল","count":"১৪"},{"name":"নাটোর","count":"১৩"},{"name":"ঝালকাঠি","count":"১৩"},{"name":"ফেনী","count":"১৩"},{"name":"ভোলা","count":"১০"},{"name":"পঞ্চগড়","count":"১০"},{"name":"পিরোজপুর","count":"৭"},{"name":"সিরাজগঞ্জ","count":"৬"},{"name":"বান্দরবান","count":"৫"},{"name":"বাগেরহাট","count":"৫"},{"name":"মেহেরপুর","count":"৫"},{"name":"সাতক্ষীরা","count":"৪"},{"name":"রাঙামাটি","count":"৪"},{"name":"খাগড়াছড়ি","count":"৩"}]
